{
  "success": false,
  "total_expectations": 22,
  "passed_expectations": 20,
  "failed_expectations": 2,
  "details": [
    {
      "type": "expect_table_row_count_to_be_between",
      "column": null,
      "success": true,
      "kwargs": {
        "batch_id": "pipeline_datasource-input_data",
        "min_value": 21000,
        "max_value": 22000
      },
      "result": {
        "observed_value": 21613
      }
    },
    {
      "type": "expect_table_columns_to_match_set",
      "column": null,
      "success": true,
      "kwargs": {
        "batch_id": "pipeline_datasource-input_data",
        "column_set": [
          "id",
          "date",
          "price",
          "bedrooms",
          "bathrooms",
          "sqft_living",
          "sqft_lot",
          "floors",
          "waterfront",
          "view",
          "condition",
          "grade",
          "sqft_above",
          "sqft_basement",
          "yr_built",
          "yr_renovated",
          "zipcode",
          "lat",
          "long",
          "sqft_living15",
          "sqft_lot15"
        ]
      },
      "result": {
        "observed_value": [
          "bathrooms",
          "bedrooms",
          "condition",
          "date",
          "floors",
          "grade",
          "id",
          "lat",
          "long",
          "price",
          "sqft_above",
          "sqft_basement",
          "sqft_living",
          "sqft_living15",
          "sqft_lot",
          "sqft_lot15",
          "view",
          "waterfront",
          "yr_built",
          "yr_renovated",
          "zipcode"
        ]
      }
    },
    {
      "type": "expect_column_values_to_be_between",
      "column": "price",
      "success": true,
      "kwargs": {
        "batch_id": "pipeline_datasource-input_data",
        "min_value": 50000.0,
        "max_value": 8000000.0
      },
      "result": {
        "element_count": 21613,
        "unexpected_count": 0,
        "unexpected_percent": 0.0,
        "partial_unexpected_list": [],
        "missing_count": 0,
        "missing_percent": 0.0,
        "unexpected_percent_total": 0.0,
        "unexpected_percent_nonmissing": 0.0,
        "partial_unexpected_counts": [],
        "partial_unexpected_index_list": []
      }
    },
    {
      "type": "expect_column_values_to_not_be_null",
      "column": "price",
      "success": true,
      "kwargs": {
        "batch_id": "pipeline_datasource-input_data",
        "mostly": 0.999
      },
      "result": {
        "element_count": 21613,
        "unexpected_count": 0,
        "unexpected_percent": 0.0,
        "partial_unexpected_list": [],
        "partial_unexpected_counts": [],
        "partial_unexpected_index_list": []
      }
    },
    {
      "type": "expect_column_values_to_be_between",
      "column": "bedrooms",
      "success": false,
      "kwargs": {
        "batch_id": "pipeline_datasource-input_data",
        "min_value": 0.0,
        "max_value": 10.0
      },
      "result": {
        "element_count": 21613,
        "unexpected_count": 2,
        "unexpected_percent": 0.009253689908851155,
        "partial_unexpected_list": [
          11,
          33
        ],
        "missing_count": 0,
        "missing_percent": 0.0,
        "unexpected_percent_total": 0.009253689908851155,
        "unexpected_percent_nonmissing": 0.009253689908851155,
        "partial_unexpected_counts": [
          {
            "value": 11,
            "count": 1
          },
          {
            "value": 33,
            "count": 1
          }
        ],
        "partial_unexpected_index_list": [
          8757,
          15870
        ]
      }
    },
    {
      "type": "expect_column_values_to_not_be_null",
      "column": "bedrooms",
      "success": true,
      "kwargs": {
        "batch_id": "pipeline_datasource-input_data",
        "mostly": 0.999
      },
      "result": {
        "element_count": 21613,
        "unexpected_count": 0,
        "unexpected_percent": 0.0,
        "partial_unexpected_list": [],
        "partial_unexpected_counts": [],
        "partial_unexpected_index_list": []
      }
    },
    {
      "type": "expect_column_values_to_be_between",
      "column": "bathrooms",
      "success": true,
      "kwargs": {
        "batch_id": "pipeline_datasource-input_data",
        "min_value": 0.0,
        "max_value": 8.0
      },
      "result": {
        "element_count": 21613,
        "unexpected_count": 0,
        "unexpected_percent": 0.0,
        "partial_unexpected_list": [],
        "missing_count": 0,
        "missing_percent": 0.0,
        "unexpected_percent_total": 0.0,
        "unexpected_percent_nonmissing": 0.0,
        "partial_unexpected_counts": [],
        "partial_unexpected_index_list": []
      }
    },
    {
      "type": "expect_column_values_to_not_be_null",
      "column": "bathrooms",
      "success": true,
      "kwargs": {
        "batch_id": "pipeline_datasource-input_data",
        "mostly": 0.999
      },
      "result": {
        "element_count": 21613,
        "unexpected_count": 0,
        "unexpected_percent": 0.0,
        "partial_unexpected_list": [],
        "partial_unexpected_counts": [],
        "partial_unexpected_index_list": []
      }
    },
    {
      "type": "expect_column_values_to_be_between",
      "column": "sqft_living",
      "success": true,
      "kwargs": {
        "batch_id": "pipeline_datasource-input_data",
        "min_value": 200.0,
        "max_value": 15000.0
      },
      "result": {
        "element_count": 21613,
        "unexpected_count": 0,
        "unexpected_percent": 0.0,
        "partial_unexpected_list": [],
        "missing_count": 0,
        "missing_percent": 0.0,
        "unexpected_percent_total": 0.0,
        "unexpected_percent_nonmissing": 0.0,
        "partial_unexpected_counts": [],
        "partial_unexpected_index_list": []
      }
    },
    {
      "type": "expect_column_values_to_not_be_null",
      "column": "sqft_living",
      "success": true,
      "kwargs": {
        "batch_id": "pipeline_datasource-input_data",
        "mostly": 0.999
      },
      "result": {
        "element_count": 21613,
        "unexpected_count": 0,
        "unexpected_percent": 0.0,
        "partial_unexpected_list": [],
        "partial_unexpected_counts": [],
        "partial_unexpected_index_list": []
      }
    },
    {
      "type": "expect_column_values_to_be_between",
      "column": "sqft_lot",
      "success": false,
      "kwargs": {
        "batch_id": "pipeline_datasource-input_data",
        "min_value": 400.0,
        "max_value": 1000000.0
      },
      "result": {
        "element_count": 21613,
        "unexpected_count": 4,
        "unexpected_percent": 0.01850737981770231,
        "partial_unexpected_list": [
          1651359,
          1074218,
          1024068,
          1164794
        ],
        "missing_count": 0,
        "missing_percent": 0.0,
        "unexpected_percent_total": 0.01850737981770231,
        "unexpected_percent_nonmissing": 0.01850737981770231,
        "partial_unexpected_counts": [
          {
            "value": 1024068,
            "count": 1
          },
          {
            "value": 1074218,
            "count": 1
          },
          {
            "value": 1164794,
            "count": 1
          },
          {
            "value": 1651359,
            "count": 1
          }
        ],
        "partial_unexpected_index_list": [
          1719,
          7647,
          7769,
          17319
        ]
      }
    },
    {
      "type": "expect_column_values_to_not_be_null",
      "column": "sqft_lot",
      "success": true,
      "kwargs": {
        "batch_id": "pipeline_datasource-input_data",
        "mostly": 0.999
      },
      "result": {
        "element_count": 21613,
        "unexpected_count": 0,
        "unexpected_percent": 0.0,
        "partial_unexpected_list": [],
        "partial_unexpected_counts": [],
        "partial_unexpected_index_list": []
      }
    },
    {
      "type": "expect_column_values_to_be_between",
      "column": "floors",
      "success": true,
      "kwargs": {
        "batch_id": "pipeline_datasource-input_data",
        "min_value": 1.0,
        "max_value": 4.0
      },
      "result": {
        "element_count": 21613,
        "unexpected_count": 0,
        "unexpected_percent": 0.0,
        "partial_unexpected_list": [],
        "missing_count": 0,
        "missing_percent": 0.0,
        "unexpected_percent_total": 0.0,
        "unexpected_percent_nonmissing": 0.0,
        "partial_unexpected_counts": [],
        "partial_unexpected_index_list": []
      }
    },
    {
      "type": "expect_column_values_to_be_in_set",
      "column": "waterfront",
      "success": true,
      "kwargs": {
        "batch_id": "pipeline_datasource-input_data",
        "value_set": [
          0,
          1
        ]
      },
      "result": {
        "element_count": 21613,
        "unexpected_count": 0,
        "unexpected_percent": 0.0,
        "partial_unexpected_list": [],
        "missing_count": 0,
        "missing_percent": 0.0,
        "unexpected_percent_total": 0.0,
        "unexpected_percent_nonmissing": 0.0,
        "partial_unexpected_counts": [],
        "partial_unexpected_index_list": []
      }
    },
    {
      "type": "expect_column_values_to_be_between",
      "column": "view",
      "success": true,
      "kwargs": {
        "batch_id": "pipeline_datasource-input_data",
        "min_value": 0.0,
        "max_value": 4.0
      },
      "result": {
        "element_count": 21613,
        "unexpected_count": 0,
        "unexpected_percent": 0.0,
        "partial_unexpected_list": [],
        "missing_count": 0,
        "missing_percent": 0.0,
        "unexpected_percent_total": 0.0,
        "unexpected_percent_nonmissing": 0.0,
        "partial_unexpected_counts": [],
        "partial_unexpected_index_list": []
      }
    },
    {
      "type": "expect_column_values_to_be_between",
      "column": "condition",
      "success": true,
      "kwargs": {
        "batch_id": "pipeline_datasource-input_data",
        "min_value": 1.0,
        "max_value": 5.0
      },
      "result": {
        "element_count": 21613,
        "unexpected_count": 0,
        "unexpected_percent": 0.0,
        "partial_unexpected_list": [],
        "missing_count": 0,
        "missing_percent": 0.0,
        "unexpected_percent_total": 0.0,
        "unexpected_percent_nonmissing": 0.0,
        "partial_unexpected_counts": [],
        "partial_unexpected_index_list": []
      }
    },
    {
      "type": "expect_column_values_to_be_between",
      "column": "grade",
      "success": true,
      "kwargs": {
        "batch_id": "pipeline_datasource-input_data",
        "min_value": 1.0,
        "max_value": 13.0
      },
      "result": {
        "element_count": 21613,
        "unexpected_count": 0,
        "unexpected_percent": 0.0,
        "partial_unexpected_list": [],
        "missing_count": 0,
        "missing_percent": 0.0,
        "unexpected_percent_total": 0.0,
        "unexpected_percent_nonmissing": 0.0,
        "partial_unexpected_counts": [],
        "partial_unexpected_index_list": []
      }
    },
    {
      "type": "expect_column_values_to_be_between",
      "column": "yr_built",
      "success": true,
      "kwargs": {
        "batch_id": "pipeline_datasource-input_data",
        "min_value": 1900.0,
        "max_value": 2020.0
      },
      "result": {
        "element_count": 21613,
        "unexpected_count": 0,
        "unexpected_percent": 0.0,
        "partial_unexpected_list": [],
        "missing_count": 0,
        "missing_percent": 0.0,
        "unexpected_percent_total": 0.0,
        "unexpected_percent_nonmissing": 0.0,
        "partial_unexpected_counts": [],
        "partial_unexpected_index_list": []
      }
    },
    {
      "type": "expect_column_values_to_be_between",
      "column": "yr_renovated",
      "success": true,
      "kwargs": {
        "batch_id": "pipeline_datasource-input_data",
        "min_value": 0.0,
        "max_value": 2020.0
      },
      "result": {
        "element_count": 21613,
        "unexpected_count": 0,
        "unexpected_percent": 0.0,
        "partial_unexpected_list": [],
        "missing_count": 0,
        "missing_percent": 0.0,
        "unexpected_percent_total": 0.0,
        "unexpected_percent_nonmissing": 0.0,
        "partial_unexpected_counts": [],
        "partial_unexpected_index_list": []
      }
    },
    {
      "type": "expect_column_values_to_not_be_null",
      "column": "zipcode",
      "success": true,
      "kwargs": {
        "batch_id": "pipeline_datasource-input_data",
        "mostly": 0.999
      },
      "result": {
        "element_count": 21613,
        "unexpected_count": 0,
        "unexpected_percent": 0.0,
        "partial_unexpected_list": [],
        "partial_unexpected_counts": [],
        "partial_unexpected_index_list": []
      }
    },
    {
      "type": "expect_column_values_to_be_between",
      "column": "lat",
      "success": true,
      "kwargs": {
        "batch_id": "pipeline_datasource-input_data",
        "min_value": 47.0,
        "max_value": 48.0
      },
      "result": {
        "element_count": 21613,
        "unexpected_count": 0,
        "unexpected_percent": 0.0,
        "partial_unexpected_list": [],
        "missing_count": 0,
        "missing_percent": 0.0,
        "unexpected_percent_total": 0.0,
        "unexpected_percent_nonmissing": 0.0,
        "partial_unexpected_counts": [],
        "partial_unexpected_index_list": []
      }
    },
    {
      "type": "expect_column_values_to_be_between",
      "column": "long",
      "success": true,
      "kwargs": {
        "batch_id": "pipeline_datasource-input_data",
        "min_value": -123.0,
        "max_value": -121.0
      },
      "result": {
        "element_count": 21613,
        "unexpected_count": 0,
        "unexpected_percent": 0.0,
        "partial_unexpected_list": [],
        "missing_count": 0,
        "missing_percent": 0.0,
        "unexpected_percent_total": 0.0,
        "unexpected_percent_nonmissing": 0.0,
        "partial_unexpected_counts": [],
        "partial_unexpected_index_list": []
      }
    }
  ]
}